laxpy/__init__.py
laxpy/clip.py
laxpy/file.py
laxpy/query.py
laxpy/tree.py
laxpytest/__init__.py
laxpytest/test_laxpy.py
laxpy-0.2.3.dist-info/LICENSE
laxpy-0.2.3.dist-info/METADATA
laxpy-0.2.3.dist-info/WHEEL
laxpy-0.2.3.dist-info/top_level.txt
laxpy-0.2.3.dist-info/RECORD
