Metadata-Version: 2.1
Name: laxpy
Version: 0.2.3
Summary: A Python API for .lax files
Home-page: https://github.com/brycefrank/laxpy
Author: Bryce Frank
Author-email: bfrank70@gmail.com
License: MIT
License-File: LICENSE
Requires-Dist: laspy
Requires-Dist: shapely
Requires-Dist: numpy
Requires-Dist: numba
